MANIFEST.in
README.rst
setup.cfg
setup.py
pypaper/__about__.py
pypaper/__init__.py
pypaper/general_tools.py
pypaper/init_project.py
pypaper/latex_tools.py
pypaper/manage.py
pypaper/py_tools.py
pypaper.egg-info/PKG-INFO
pypaper.egg-info/SOURCES.txt
pypaper.egg-info/dependency_links.txt
pypaper.egg-info/not-zip-safe
pypaper.egg-info/requires.txt
pypaper.egg-info/top_level.txt
pypaper/templates/__init__.py
pypaper/templates/all_paths.py
pypaper/templates/base-paper.tex
pypaper/templates/fig_functions.py
pypaper/templates/figure_template.py
pypaper/templates/generate_bibtex_file.py
pypaper/templates/pre-commit-hook.sh
pypaper/templates/settings.py
pypaper/templates/user_paths.py