Metadata-Version: 2.1
Name: pypaper
Version: 0.3.6
Summary: A command line tool to aid the writing of research papers
Home-page: https://github.com/eng-tools/pypaper
Author: Maxim Millen
Author-email: mmi46@uclive.ac.nz
License: MIT
Keywords: research latex
Platform: UNKNOWN
Classifier: Development Status :: 3 - Alpha
Classifier: Intended Audience :: Science/Research
Classifier: Topic :: Scientific/Engineering
Classifier: License :: OSI Approved :: MIT License
Classifier: Programming Language :: Python :: 3
Requires-Python: >=3
Provides-Extra: test
